mushan/__init__.py
mushan/audio/__init__.py
mushan/audio/audio.py
mushan/audio/data.py
mushan/audio/dataset.py
mushan/audio/encodrc.py
mushan/audio/lhotse.py
mushan/audio/plot.py
mushan/audio/spec_process.py
mushan/dl/__init__.py
mushan/dl/activation.py
mushan/dl/func.py
mushan/dl/loss.py
mushan/io/__init__.py
mushan/log/__init__.py
mushan/log/func.py
mushan/loss/__init__.py
mushan/ml/__init__.py
mushan/ml/func.py
mushan/nb/__init__.py
mushan/src/temp.txt
mushan/tool/__init__.py
mushan/tool/func.py
mushan-0.0.13.dist-info/LICENSE
mushan-0.0.13.dist-info/METADATA
mushan-0.0.13.dist-info/WHEEL
mushan-0.0.13.dist-info/entry_points.txt
mushan-0.0.13.dist-info/top_level.txt
mushan-0.0.13.dist-info/zip-safe
mushan-0.0.13.dist-info/RECORD
