Metadata-Version: 2.1
Name: mushan
Version: 0.0.13
Summary: Personal toolkit.
Home-page: https://github.com/mushanshanshan/mushan-pip
Author: Mushan
Author-email: wwd137669793@gmail.com
License: None
Classifier: Programming Language :: Python :: 3
Classifier: License :: OSI Approved :: MIT License
Classifier: Operating System :: OS Independent
Requires-Python: >=3.6
License-File: LICENSE
Requires-Dist: Cython
Requires-Dist: librosa
Requires-Dist: matplotlib
Requires-Dist: numpy
Requires-Dist: phonemizer
Requires-Dist: scipy
Requires-Dist: tensorboard
Requires-Dist: Unidecode
Requires-Dist: p-tqdm
Requires-Dist: varname
Requires-Dist: tqdm
Requires-Dist: loguru
Requires-Dist: dotmap
Requires-Dist: inflect
Requires-Dist: encodec
Requires-Dist: lhotse
Requires-Dist: torchaudio
